teneva_opti/__init__.py
teneva_opti/bm_view.py
teneva_opti/opti.py
teneva_opti/opti_func.py
teneva_opti/opti_manager.py
teneva_opti/opti_tens.py
teneva_opti/plot.py
teneva_opti/utils.py
teneva_opti/func/__init__.py
teneva_opti/tens/__init__.py
teneva_opti/tens/opti_tens_nb.py
teneva_opti/tens/opti_tens_opo.py
teneva_opti/tens/opti_tens_optimatt.py
teneva_opti/tens/opti_tens_portfolio.py
teneva_opti/tens/opti_tens_protes.py
teneva_opti/tens/opti_tens_pso.py
teneva_opti/tens/opti_tens_spsa.py
teneva_opti/tens/opti_tens_ttopt.py
teneva_opti-0.6.0.dist-info/LICENSE
teneva_opti-0.6.0.dist-info/METADATA
teneva_opti-0.6.0.dist-info/WHEEL
teneva_opti-0.6.0.dist-info/top_level.txt
teneva_opti-0.6.0.dist-info/RECORD
