Metadata-Version: 2.1
Name: teneva_opti
Version: 0.6.0
Summary: Collection of various optimization methods, including tensor based, for multivariate functions and multidimensional data arrays
Home-page: https://github.com/AIRI-Institute/teneva_opti
Author: Andrei Chertkov
Author-email: andre.chertkov@gmail.com
License: MIT
Project-URL: Source, https://github.com/AIRI-Institute/teneva_opti
Keywords: optimization method multidimensional array multivariate function tensor train nevergrad cma ttopt protes genetic algorithm evolutionary strategy
Classifier: Development Status :: 3 - Alpha
Classifier: License :: OSI Approved :: MIT License
Classifier: Topic :: Scientific/Engineering
Classifier: Topic :: Scientific/Engineering :: Mathematics
Classifier: Topic :: Scientific/Engineering :: Information Analysis
Classifier: Topic :: Scientific/Engineering :: Artificial Intelligence
Classifier: Intended Audience :: Science/Research
Classifier: Operating System :: OS Independent
Classifier: Programming Language :: Python :: 3
Classifier: Programming Language :: Python :: 3 :: Only
Classifier: Programming Language :: Python :: 3.8
Classifier: Programming Language :: Python :: 3.9
Requires-Python: >=3.8
License-File: LICENSE
Requires-Dist: nevergrad ==0.8.0
Requires-Dist: pandas <=1.5.3
Requires-Dist: protes ==0.3.6
Requires-Dist: seaborn ==0.12.2
Requires-Dist: teneva >=0.14.7
Requires-Dist: teneva-bm ==0.9.0
Requires-Dist: ttopt ==0.6.2
Requires-Dist: contourpy ==1.1.1 ; python_version == "3.8"
Requires-Dist: matplotlib <3.7.1,>=3.7.0 ; python_version == "3.8"
Requires-Dist: ml-dtypes <=0.2.0 ; python_version == "3.8"
Requires-Dist: numpy <1.25,>=1.22 ; python_version == "3.8"
Requires-Dist: scikit-learn <=1.3.2 ; python_version == "3.8"
Requires-Dist: scipy <1.11,>=1.9 ; python_version == "3.8"
Requires-Dist: matplotlib >=3.7.0 ; python_version >= "3.9"
Requires-Dist: ml-dtypes ; python_version >= "3.9"
Requires-Dist: numpy >=1.22 ; python_version >= "3.9"
